AUTHORS.rst
CONTRIBUTING.rst
HISTORY.rst
LICENSE
MANIFEST.in
README.rst
setup.cfg
setup.py
docs/Makefile
docs/authors.rst
docs/conf.py
docs/contributing.rst
docs/history.rst
docs/index.rst
docs/installation.rst
docs/make.bat
docs/readme.rst
docs/usage.rst
snp_mutator.egg-info/PKG-INFO
snp_mutator.egg-info/SOURCES.txt
snp_mutator.egg-info/dependency_links.txt
snp_mutator.egg-info/entry_points.txt
snp_mutator.egg-info/not-zip-safe
snp_mutator.egg-info/requires.txt
snp_mutator.egg-info/top_level.txt
snpmutator/__init__.py
snpmutator/script.py
snpmutator/vcf_writer.py
tests/__init__.py
tests/test.sh
tests/test_snpmutator.py