Metadata-Version: 1.1
Name: snp-mutator
Version: 1.2.0
Summary: Generate mutated sequence files from a reference genome.
Home-page: https://github.com/CFSAN-Biostatistics/snp-mutator
Author: Hugh Rand
Author-email: Hugh.Rand@fda.hhs.gov
License: BSD
Keywords: bioinformatics,NGS,snp-mutator
Platform: UNKNOWN
Classifier: Development Status :: 2 - Pre-Alpha
Classifier: Intended Audience :: Developers
Classifier: License :: OSI Approved :: BSD License
Classifier: Natural Language :: English
Classifier: Programming Language :: Python :: 2
Classifier: Programming Language :: Python :: 2.6
Classifier: Programming Language :: Python :: 2.7
Classifier: Programming Language :: Python :: 3
Classifier: Programming Language :: Python :: 3.3
Classifier: Programming Language :: Python :: 3.4
